gdeltnews/__init__.py
gdeltnews/download.py
gdeltnews/filtermerge.py
gdeltnews/reconstruct.py
gdeltnews/wordmatch.py
gdeltnews-1.0.0.dist-info/licenses/LICENSE
gdeltnews-1.0.0.dist-info/METADATA
gdeltnews-1.0.0.dist-info/WHEEL
gdeltnews-1.0.0.dist-info/top_level.txt
gdeltnews-1.0.0.dist-info/RECORD
