Metadata-Version: 2.4
Name: gdeltnews
Version: 1.0.0
Summary: Reconstruct full-text news articles from GDELT Web News NGrams 3.0
Author: Andrea Fronzetti Colladon, Roberto Vestrelli
License:                     GNU GENERAL PUBLIC LICENSE
Project-URL: Homepage, https://github.com/iandreafc/gdeltnews
Project-URL: Repository, https://github.com/iandreafc/gdeltnews
Keywords: gdelt,webngrams,news,nlp
Classifier: Programming Language :: Python :: 3
Classifier: License :: OSI Approved :: GNU General Public License v3 (GPLv3)
Requires-Python: >=3.9
License-File: LICENSE
Requires-Dist: requests>=2.0
Requires-Dist: tqdm>=4.0
Requires-Dist: boolean.py>=5.0
Dynamic: license-file
